clustercontroller/__init__.py
clustercontroller/backup.py
clustercontroller/clustercontroller.py
docker_cluster_controller-0.1.28.dist-info/METADATA
docker_cluster_controller-0.1.28.dist-info/WHEEL
docker_cluster_controller-0.1.28.dist-info/top_level.txt
docker_cluster_controller-0.1.28.dist-info/RECORD
