Metadata-Version: 2.1
Name: docker-cluster-controller
Version: 0.1.28
Summary: A simple Python class to orchestrate cluster nodes within a docker environment.
Home-page: https://github.com/erikdewildt/docker-cluster-controller
Author: erik.de.wildt
Author-email: erik.de.wildt@gmail.com
License: GNU GENERAL PUBLIC LICENSE
Platform: UNKNOWN
Classifier: Development Status :: 4 - Beta
Classifier: Intended Audience :: Developers
Classifier: License :: OSI Approved :: GNU General Public License v3 or later (GPLv3+)
Classifier: Operating System :: OS Independent
Classifier: Programming Language :: Python
Classifier: Programming Language :: Python :: 3
Classifier: Topic :: System :: Clustering
Requires-Dist: Jinja2 (>=2.10.1)
Requires-Dist: python-etcd (>=0.4.5)
Requires-Dist: schedule (>=0.6.0)
Requires-Dist: sentry-sdk (>=0.11.2)
Requires-Dist: func-timeout (>=4.3.3)
